gymnax/__init__.py
gymnax/registration.py
gymnax/environments/__init__.py
gymnax/environments/environment.py
gymnax/environments/spaces.py
gymnax/environments/bsuite/__init__.py
gymnax/environments/bsuite/bandit.py
gymnax/environments/bsuite/catch.py
gymnax/environments/bsuite/deep_sea.py
gymnax/environments/bsuite/discounting_chain.py
gymnax/environments/bsuite/memory_chain.py
gymnax/environments/bsuite/mnist.py
gymnax/environments/bsuite/umbrella_chain.py
gymnax/environments/classic_control/__init__.py
gymnax/environments/classic_control/acrobot.py
gymnax/environments/classic_control/cartpole.py
gymnax/environments/classic_control/continuous_mountain_car.py
gymnax/environments/classic_control/mountain_car.py
gymnax/environments/classic_control/pendulum.py
gymnax/environments/minatar/__init__.py
gymnax/environments/minatar/asterix.py
gymnax/environments/minatar/breakout.py
gymnax/environments/minatar/freeway.py
gymnax/environments/minatar/seaquest.py
gymnax/environments/minatar/space_invaders.py
gymnax/environments/misc/__init__.py
gymnax/environments/misc/bernoulli_bandit.py
gymnax/environments/misc/gaussian_bandit.py
gymnax/environments/misc/meta_maze.py
gymnax/environments/misc/point_robot.py
gymnax/environments/misc/pong.py
gymnax/environments/misc/reacher.py
gymnax/environments/misc/rooms.py
gymnax/environments/misc/swimmer.py
gymnax/experimental/__init__.py
gymnax/experimental/rollout.py
gymnax/utils/load_mnist.py
gymnax/visualize/__init__.py
gymnax/visualize/vis_catch.py
gymnax/visualize/vis_circle.py
gymnax/visualize/vis_gym.py
gymnax/visualize/vis_maze.py
gymnax/visualize/vis_minatar.py
gymnax/visualize/visualizer.py
gymnax/wrappers/__init__.py
gymnax/wrappers/brax.py
gymnax/wrappers/dm_env.py
gymnax/wrappers/evojax.py
gymnax/wrappers/gym.py
gymnax/wrappers/purerl.py
gymnax-0.0.9.dist-info/METADATA
gymnax-0.0.9.dist-info/WHEEL
gymnax-0.0.9.dist-info/top_level.txt
gymnax-0.0.9.dist-info/RECORD
