Metadata-Version: 2.4
Name: gymnax
Version: 0.0.9
Summary: JAX implementations of OpenAI's gym environments
Author-email: Robert Tjarko Lange <robertlange0@gmail.com>
License: Apache-2.0
Project-URL: Homepage, https://github.com/RobertTLange/gymnax
Classifier: Programming Language :: Python :: 3.10
Classifier: Programming Language :: Python :: 3.11
Classifier: Programming Language :: Python :: 3.12
Classifier: Programming Language :: Python :: 3.13
Classifier: License :: OSI Approved :: Apache Software License
Classifier: Operating System :: OS Independent
Classifier: Topic :: Scientific/Engineering :: Artificial Intelligence
Requires-Python: >=3.10
Requires-Dist: jax
Requires-Dist: flax
Requires-Dist: gymnasium
Requires-Dist: matplotlib
Requires-Dist: seaborn
Provides-Extra: dev
Requires-Dist: pytest; extra == "dev"
Requires-Dist: pytest-cov; extra == "dev"
Requires-Dist: ruff; extra == "dev"
Requires-Dist: mypy; extra == "dev"
Provides-Extra: test
Requires-Dist: chex; extra == "test"
Requires-Dist: flax; extra == "test"
Requires-Dist: brax; extra == "test"
Requires-Dist: minatar; extra == "test"
